{
  "common.language": "भाषा",
  "common.back": "वापस",
  "common.close": "बंद करें",
  "common.copy": "कॉपी करें",
  "common.copySuccess": "सफलतापूर्वक कॉपी हुआ",
  "common.copyFail": "कॉपी विफल",
  "common.download": "डाउनलोड",
  "common.upload": "अपलोड",
  "common.delete": "हटाएं",
  "common.cancel": "रद्द करें",
  "common.confirm": "पुष्टि करें",
  "common.copied": "कॉपी हुआ",
  "nav.home": "होम",
  "nav.calc": "गणना",
  "nav.query": "खोज",
  "nav.traditional": "पारंपरिक",
  "nav.picker": "पिकर",
  "theme.light": "हल्का",
  "theme.dark": "गहरा",
  "theme.system": "सिस्टम",
  "sidebar.customSoftware": "कस्टम सॉफ्टवेयर",
  "sidebar.feedback": "फीडबैक",
  "sidebar.shortcutHelp": "शॉर्टकट",
  "sidebar.checkUpdate": "अपडेट जांचें",
  "shortcut.title": "ग्लोबल शॉर्टकट",
  "shortcut.hint": "ऐप के बाहर काम करता है। Mac पर Ctrl के बजाय ⌘ इस्तेमाल करें।",
  "shortcut.shortcutCol": "शॉर्टकट",
  "shortcut.actionCol": "क्रिया",
  "shortcut.screenPick": "स्क्रीन पिकर",
  "shortcut.colorblind": "कलर ब्लाइंड सिम्युलेटर",
  "shortcut.palette": "पैलेट मैनेजर",
  "shortcut.showHide": "विंडो दिखाएं / छिपाएं",
  "auth.loginRegister": "लॉगिन / रजिस्टर",
  "auth.welcomeBack": "वापस स्वागत है",
  "auth.syncAccount": "अधिक सुविधाओं के लिए वेब अकाउंट से सिंक करें",
  "auth.goLogin": "लॉगिन पर जाएं",
  "auth.cancelLogin": "लॉगिन रद्द करें",
  "auth.logout": "लॉग आउट",
  "auth.member": "कुनकिओंग कलर वर्कशॉप सदस्य",
  "auth.syncing": "लॉगिन सिंक हो रहा है...",
  "auth.syncingHint": "खुले ब्राउज़र में चरण पूरे करें। होने पर यह विंडो रिफ्रेश हो जाएगी।",
  "toast.copySuccessGrayscale": "ग्रेस्केल कॉपी हुआ: {{value}}",
  "toast.copySuccessOpposite": "विपरीत रंग कॉपी हुआ: {{value}}",
  "toast.copySuccessMixed": "मिश्रित रंग कॉपी हुआ: {{value}}",
  "toast.copySuccessHex": "HEX कॉपी हुआ: {{value}}",
  "toast.copySuccessRgb": "RGB कॉपी हुआ: {{value}}",
  "toast.copySuccessColor": "रंग कॉपी हुआ: {{value}}",
  "toast.copySuccessPlain": "कॉपी हुआ: {{value}}",
  "toast.copyFailRetry": "कॉपी विफल, कृपया पुनः प्रयास करें",
  "app.pageNotFound": "पेज नहीं मिला (404)",
  "home.title": "होम",
  "home.badge": "प्रोफेशनल कलर डिज़ाइन असिस्टेंट",
  "home.brand": "कलर वर्कशॉप",
  "home.slogan": "रंग की अनंत संभावनाओं का अन्वेषण करें",
  "home.featureTraditional": "पारंपरिक रंग",
  "home.featureTraditionalDesc": "चीनी और जापानी पारंपरिक पैलेट।",
  "home.featurePicker": "कलर पिकर",
  "home.featurePickerDesc": "इमेज और स्क्रीन से रंग चुनना।",
  "home.featureCalc": "गणना",
  "home.featureCalcDesc": "कंट्रास्ट, ग्रेस्केल, रंग मिश्रण।",
  "home.featureQuery": "खोज",
  "home.featureQueryDesc": "फॉर्मेट रूपांतरण, वेब-सेफ रंग, ग्रेडिएंट।",
  "home.advantageFast": "तेज़",
  "home.advantageFastDesc": "सभी प्रोसेसिंग लोकल।",
  "home.advantageSafe": "प्राइवेट",
  "home.advantageSafeDesc": "केवल लोकल, आपका डेटा सुरक्षित।",
  "home.advantageSmooth": "सुचारू",
  "home.advantageSmoothDesc": "पॉलिश्ड UI और वर्कफ्लो।",
  "home.footer": "कलर वर्कशॉप | Kunqiong AI",
  "calc.title": "रंग गणना",
  "calc.grayscale": "इमेज से ग्रेस्केल",
  "calc.grayscaleDesc": "रंगीन इमेज को ग्रेस्केल में बदलें।",
  "calc.colorGrayscale": "रंग से ग्रेस्केल",
  "calc.colorGrayscaleDesc": "एक रंग को ग्रेस्केल में बदलें।",
  "calc.mix": "रंग मिश्रण",
  "calc.mixDesc": "अनुपात से दो रंग मिलाएं।",
  "calc.intermediate": "बीच के रंग",
  "calc.intermediateDesc": "दो रंगों के बीच स्टेप जनरेट करें।",
  "calc.contrast": "कंट्रास्ट चेक",
  "calc.contrastDesc": "फोरग्राउंड/बैकग्राउंड कंट्रास्ट चेक (WCAG)।",
  "calc.colorblind": "कलर ब्लाइंड सिम्युलेटर",
  "calc.colorblindDesc": "प्रोटानोपिया, ड्यूटेरानोपिया, ट्राइटानोपिया सिम्युलेट करें।",
  "calc.opposite": "विपरीत रंग",
  "calc.oppositeDesc": "पूरक रंग पाएं (ह्यू व्हील पर 180°)।",
  "calcGrayscale.title": "ग्रेस्केल रूपांतरण",
  "calcGrayscale.originalColor": "मूल रंग",
  "calcGrayscale.grayscaleResult": "ग्रेस्केल परिणाम",
  "calcGrayscale.copyGrayscale": "ग्रेस्केल कॉपी करें",
  "calcGrayscale.whatIsTitle": "ग्रेस्केल क्या है?",
  "calcGrayscale.whatIsDesc": "ग्रेस्केल रूपांतरण ल्यूमिनेंस वेटिंग इस्तेमाल करता है। UI में हायरार्की और कंट्रास्ट चेक के लिए उपयोगी।",
  "calcImageGrayscale.title": "इमेज से ग्रेस्केल",
  "calcImageGrayscale.originalImage": "मूल इमेज",
  "calcImageGrayscale.deleteImage": "इमेज हटाएं",
  "calcImageGrayscale.uploadFirst": "पहले इमेज अपलोड करें",
  "calcImageGrayscale.uploadFormat": "JPG, PNG, WebP सपोर्टेड",
  "calcImageGrayscale.uploadImage": "इमेज अपलोड करें",
  "calcImageGrayscale.result": "परिणाम",
  "calcImageGrayscale.resultPreview": "परिणाम प्रीव्यू",
  "calcImageGrayscale.downloadImage": "इमेज डाउनलोड करें",
  "calcImageGrayscale.aboutTitle": "इस टूल के बारे में:",
  "calcImageGrayscale.about1": "1. रंगीन इमेज जोड़ने के लिए \"इमेज अपलोड करें\" क्लिक करें।",
  "calcImageGrayscale.about2": "2. यह ऑटोमैटिक ग्रेस्केल में बदल जाएगी।",
  "calcImageGrayscale.about3": "3. सेव करने के लिए \"इमेज डाउनलोड करें\" क्लिक करें।",
  "calcImageGrayscale.about4": "4. प्रोसेसिंग लोकल है; इमेज अपलोड नहीं होती।",
  "calcMix.title": "रंग मिक्सर",
  "calcMix.pageTitle": "दो-रंग मिक्सर",
  "calcMix.color1": "रंग 1",
  "calcMix.color2": "रंग 2",
  "calcMix.ratio": "अनुपात",
  "calcMix.mixedResult": "मिश्रित परिणाम",
  "calcMix.aboutTitle": "इस टूल के बारे में:",
  "calcMix.about1": "1. नया रंग पाने के लिए दो रंग मिलाएं।",
  "calcMix.about2": "2. दो रंग एंटर या चुनें; परिणाम रियल टाइम अपडेट।",
  "calcMix.about3": "3. HEX और RGB आउटपुट; ज़रूरत हो तो वेब-सेफ सुझाव।",
  "calcIntermediate.title": "बीच के रंग",
  "calcIntermediate.pageTitle": "इंटरमीडिएट रंग जनरेटर",
  "calcIntermediate.startColor": "शुरू रंग",
  "calcIntermediate.endColor": "अंत रंग",
  "calcIntermediate.stepCount": "स्टेप: {{count}}",
  "calcIntermediate.gradientTitle": "जनरेटेड ग्रेडिएंट",
  "calcIntermediate.aboutTitle": "इस टूल के बारे में:",
  "calcIntermediate.about1": "1. शुरू और अंत रंग के बीच स्मूथ स्टेप जनरेट करता है।",
  "calcIntermediate.about2": "2. पैलेट और UI ग्रेडिएंट के लिए स्टेप काउंट (1–15) एडजस्ट करें।",
  "calcIntermediate.about3": "3. HEX कॉपी करने के लिए किसी स्वैच पर क्लिक करें।",
  "calcContrast.title": "कंट्रास्ट चेक",
  "calcContrast.pageTitle": "कंट्रास्ट और मैच चेक",
  "calcContrast.subtitle": "समानता और पठनीयता का विश्लेषण",
  "calcContrast.background": "बैकग्राउंड",
  "calcContrast.foreground": "फोरग्राउंड",
  "calcContrast.matchRating": "मैच",
  "calcContrast.perfect": "परफेक्ट",
  "calcContrast.highMatch": "हाई",
  "calcContrast.basicMatch": "ठीक",
  "calcContrast.lowMatch": "लो",
  "calcContrast.suggestChange": "बदलाव सुझाया गया",
  "calcContrast.wcagAA": "WCAG AA",
  "calcContrast.wcagAAA": "WCAG AAA",
  "calcContrast.pass": "पास",
  "calcContrast.fail": "फेल",
  "calcContrast.previewText": "प्रीव्यू",
  "calcContrast.previewDesc": "कलर वर्कशॉप पठनीय, सामंजस्यपूर्ण UI बनाने में मदद करता है।",
  "calcContrast.primaryBtn": "प्राइमरी बटन",
  "calcContrast.invertBtn": "इन्वर्टेड",
  "calcContrast.contrastScore": "कंट्रास्ट स्कोर",
  "calcContrast.matchScore": "मैच स्कोर",
  "calcContrast.comprehensiveEval": "समग्र",
  "calcContrast.colorSimilarity": "समानता",
  "calcContrast.labPerception": "Lab परसेप्शन",
  "calcContrast.matchSuggestion": "सुझाव",
  "calcContrast.matchHint1": "रंग बहुत समान; हार्मनी के लिए अच्छा लेकिन टेक्स्ट कंट्रास्ट चेक करें।",
  "calcContrast.matchHint2": "अच्छा अंतर; अगर कंट्रास्ट ≥ 4.5 तो यह संतुलित जोड़ी है।",
  "calcContrast.matchHint3": "मजबूत कंट्रास्ट; एम्फेसिस और पठनीय टेक्स्ट के लिए अच्छा।",
  "calcContrast.aboutTitle": "कंट्रास्ट और मैच के बारे में:",
  "calcContrast.about1": "1. WCAG कंट्रास्ट और Lab समानता को जोड़ता है।",
  "calcContrast.about2": "2. समानता Lab दूरी है (100% = समान)।",
  "calcContrast.about3": "3. AA (4.5:1) टेक्स्ट के लिए बेसलाइन; AAA (7:1) बेहतर।",
  "calcContrast.about4": "4. हार्मनी (समानता) और पठनीयता (कंट्रास्ट) का संतुलन।",
  "calcOpposite.title": "विपरीत रंग",
  "calcOpposite.originalColor": "मूल",
  "calcOpposite.oppositeColor": "विपरीत (पूरक)",
  "calcOpposite.copyOpposite": "विपरीत कॉपी करें",
  "calcOpposite.whatIsTitle": "विपरीत रंग क्या है?",
  "calcOpposite.whatIsDesc": "ह्यू व्हील पर 180° का रंग। मजबूत कंट्रास्ट; अलर्ट और एम्फेसिस के लिए अच्छा।",
  "calcColorblind.title": "कलर ब्लाइंड सिम्युलेटर",
  "calcColorblind.singleColor": "सिंगल रंग",
  "calcColorblind.imageMode": "इमेज",
  "calcColorblind.protanopia": "प्रोटानोपिया",
  "calcColorblind.deuteranopia": "ड्यूटेरानोपिया",
  "calcColorblind.tritanopia": "ट्राइटानोपिया",
  "calcColorblind.chooseColor": "रंग चुनें",
  "calcColorblind.normalVision": "नॉर्मल",
  "calcColorblind.selectImage": "इमेज चुनें",
  "calcColorblind.processing": "प्रोसेस हो रहा है…",
  "calcColorblind.aboutTitle": "कलर ब्लाइंड सिम्युलेशन के बारे में",
  "calcColorblind.aboutDesc": "एक्सेसिबिलिटी के लिए sRGB मैट्रिक्स से प्रोटानोपिया, ड्यूटेरानोपिया, ट्राइटानोपिया सिम्युलेट करता है।",
  "query.title": "रंग खोज और टूल",
  "query.convert": "रंग रूपांतरण",
  "query.convertDesc": "HEX, RGB, CMYK, HSL, HSV के बीच रूपांतरण।",
  "query.picker": "कलर पिकर",
  "query.pickerDesc": "कई कलर स्पेस के साथ रिच पिकर।",
  "query.gradients": "ग्रेडिएंट",
  "query.gradientsDesc": "क्यूरेटेड ग्रेडिएंट; एक क्लिक में CSS कॉपी।",
  "query.websafe": "वेब सेफ रंग",
  "query.websafeDesc": "216 क्लासिक वेब-सेफ रंग।",
  "query.rgbReference": "RGB रेफरेंस",
  "query.rgbReferenceDesc": "RGB वैल्यू और CSS; एक क्लिक में कॉपी।",
  "query.cmykReference": "CMYK रेफरेंस",
  "query.cmykReferenceDesc": "प्रिंट डिज़ाइन के लिए CMYK वैल्यू।",
  "query.palettes": "पैलेट मैनेजर",
  "query.palettesDesc": "पैलेट सेव और मैनेज; इंपोर्ट/एक्सपोर्ट।",
  "traditional.title": "पारंपरिक रंग",
  "traditional.china": "चीनी पारंपरिक",
  "traditional.chinaDesc": "क्लासिक चीनी रंग पैलेट।",
  "traditional.japan": "जापानी पारंपरिक",
  "traditional.japanDesc": "क्लासिक जापानी रंग पैलेट।",
  "picker.title": "कलर पिकर",
  "picker.image": "इमेज पिकर",
  "picker.imageDesc": "इमेज अपलोड करें और पिक्सल रंग चुनें।",
  "picker.screen": "स्क्रीन पिकर",
  "picker.screenDesc": "स्क्रीन पर कोई भी पिक्सल चुनें।",
  "pickerImage.title": "इमेज कलर पिकर",
  "pickerImage.previewArea": "प्रीव्यू",
  "pickerImage.pickResult": "चुना हुआ रंग",
  "pickerImage.uploadFirst": "पहले इमेज अपलोड करें",
  "pickerImage.uploadFormat": "JPG, PNG, WebP सपोर्टेड",
  "pickerImage.deleteImage": "इमेज हटाएं",
  "pickerImage.uploadImage": "इमेज अपलोड करें",
  "pickerImage.pickHint": "रंग चुनने के लिए इमेज पर क्लिक करें",
  "pickerImage.currentColor": "वर्तमान",
  "pickerImage.history": "इतिहास",
  "pickerImage.aboutTitle": "इस टूल के बारे में:",
  "pickerImage.about1": "1. पिकर में रंग चुनें।",
  "pickerImage.about2": "2. HEX/RGB और संबंधित वैल्यू देखें।",
  "pickerImage.about3": "3. ट्रांसपेरेंसी सपोर्टेड।",
  "pickerImage.about4": "4. डिस्प्ले मॉनिटर से अलग हो सकता है।",
  "pickerScreen.title": "स्क्रीन कलर पिकर",
  "pickerScreen.screenPickTitle": "स्क्रीन पिकर",
  "pickerScreen.screenPickDesc": "स्क्रीन पर कोई पिक्सल चुनने के लिए बटन क्लिक करें।",
  "pickerScreen.startPick": "चुनना शुरू करें",
  "pickerScreen.eyeDropperNotSupported": "EyeDropper API सपोर्टेड नहीं। आधुनिक ब्राउज़र या Electron इस्तेमाल करें।",
  "queryConvert.title": "रंग रूपांतरण",
  "queryPicker.title": "कलर पिकर",
  "queryGradients.title": "ग्रेडिएंट",
  "queryGradients.copyCss": "CSS कॉपी करें",
  "queryWebsafe.title": "वेब सेफ रंग",
  "queryRgb.title": "RGB रेफरेंस",
  "queryRgb.colorSearch": "रंग खोज",
  "queryRgb.colorSample": "नमूना",
  "queryRgb.englishName": "नाम",
  "queryRgb.rgbColor": "RGB",
  "queryRgb.hex": "Hex",
  "queryRgb.colorEffect": "प्रीव्यू",
  "queryRgb.hexValue": "Hex",
  "queryCmyk.title": "CMYK रेफरेंस",
  "queryCmyk.number": "क्र.",
  "queryCmyk.hexValue": "Hex",
  "queryPalette.title": "पैलेट मैनेजर",
  "queryPalette.currentPicked": "वर्तमान रंग:",
  "queryPalette.addToPalette": "नीचे किसी पैलेट में जोड़ें, या",
  "queryPalette.noPalette": "अभी कोई पैलेट नहीं",
  "queryPalette.noPaletteHint": "रंग सेव और इंपोर्ट/एक्सपोर्ट के लिए पैलेट बनाएं",
  "queryPalette.exportPalette": "पैलेट एक्सपोर्ट करें",
  "queryPalette.deletePalette": "पैलेट हटाएं",
  "queryPalette.clickCopy": "कॉपी के लिए क्लिक करें",
  "queryPalette.addColor": "रंग जोड़ें",
  "common.colorsCount": "{{count}} ???",
  "traditional.chinaAboutTitle": "???? ???????? ????? ?? ???? ???:",
  "traditional.chinaAbout1": "1. ???? ???????? ??? ???????? ?????? ?? ?? ???? ???? ???????? ?????? ???",
  "traditional.chinaAbout2": "2. ???? ???? ???????? ?? ??? ??????? ??? ?? ???? ??????????? ???? ??? ?? ???:",
  "traditional.chinaAboutItem1": "(1) ???: ????, ???????, ?????? ?? ??????? ?? ??????; ????????? ?? ?????????? ?????? ?? ?????? ??? ?? ????? ???? ???",
  "traditional.chinaAboutItem2": "(2) ????: ??????? ??? ??? ?? ???? ??? ??; ?? ??????, ????? ?? ??????? ?? ?????? ???",
  "traditional.chinaAboutItem3": "(3) ????: ???-??? ???????? ?? ?????? ?? ????? ???? ??; ?? ???? ?? ????? ?? ?? ?????? ???",
  "traditional.chinaAboutItem4": "(4) ???: ????, ?????? ?? ??? ?? ????? ??; ?? ?????? ?? ??????? ?? ?? ???????????? ???? ???",
  "traditional.chinaAboutItem5": "(5) ????: ???-??? ??, ????? ?? ??? ?? ????? ???? ??; ?? ??????? ?? ????????? ?? ?????? ???? ???",
  "traditional.chinaAboutItem6": "(6) ????: ???????? ?? ??? ?? ????? ??; ???????? ??? ?? ?????? ?? ??? ??? ?????? ???? ??? ????? ??? ???",
  "traditional.chinaAboutItem7": "(7) ??????: ???????? ?? ??????? ?? ??????; ???-??? ????? ?? ???????? ?? ?? ????? ???? ???",
  "traditional.chinaAboutItem8": "(8) ??????: ??, ??????? ?? ????????? ?? ??????; ????? ??? ????? ????? ???? ???",
  "traditional.chinaAboutItem9": "(9) ???: ???? ??? ?????? ????, ????? ????? ?? ???? ???? ?? ?????? ???? ???",
  "traditional.chinaAbout3": "3. ???????? ??? ????????, ?????????, ??????, ??????? ?? ????? ???? ??? ????? ???? ???, ?? ???? ???????? ?? ?????????? ?????? ????",
  "traditional.japanCategoryDefault": "??????? ???",
  "traditional.japanTitle": "?????? ???????? ??? (Washoku)",
  "traditional.japanAboutTitle": "?????? ???????? ????? (Nippon Colors) ?? ???? ???:",
  "traditional.japanAbout1": "1. ?????? ???????? ??? ?? ??? ???, ?? ???? ??? ?? ????????, ????? ?? ????? ???? ???????? ????? ?? ??????? ??? ????? ???? ??? ????",
  "traditional.japanAbout2": "2. ???? ??? ????? ??????? ???? ???, ?????, ???, ???? ?? ????? ???? ?? ??????? ?? ??? ???:",
  "traditional.japanAboutItem1": "(1) Sakura-iro: ???? ?? ???? ?????? ?? ??????; ?????? ?????????? ?? ?? ????? ????",
  "traditional.japanAboutItem2": "(2) Akane-iro: ?? ??????? ??? ???; ????? ????????? ?? ??? ????? ??? ????? ???? ???",
  "traditional.japanAboutItem3": "(3) Ruri-iro: ???? ????; ?????? ?? ???? ?? ???????",
  "traditional.japanAboutItem4": "(4) Matcha-iro: ??? ?????? ?? ??????? ???, ?? ????-???? ?? ??????? ?? ??????? ???",
  "traditional.japanAbout3": "3. ?? ??? ????? ????? ???? ???? ???, ????? ??? ???????? ?? ??????? ??? ?? ????? ??? ???; ?? ??? ?? ???? ????, ??????? ?? ?????? ?? ?? ????? ???",
  "pickerScreen.recent": "??? ?? ???",
  "pickerScreen.tipsTitle": "?????",
  "pickerScreen.tipsDesc": "EyeDropper API ???? ???? ???????? ?? ??? ????? ???? ??? Electron ??????? ??? ?? ??????? ?? ???? ?? ?? ??? ??? ?? ??? ?? ???? ???? ????? ?? ???, ??? ?????????? ??? ???? ???? ?? ??? ??? ?? ????? ?????",
  "queryConvert.savedToPalette": "??????? ??? ????? ???, ????? ?????? ???? ?? ??? ??",
  "queryConvert.unknownName": "??????",
  "queryConvert.aboutTitle": "??? ???????? ?? ???? ???:",
  "queryConvert.about1": "1. HEX, RGB, HSL ?? HSV ???? ??????? ??? ??????? ?? ??? ?? ??? ?? ????? ?? ????????? ?????",
  "queryConvert.about2": "2. ???? HEX ??? ???? ???? ?? ???? ?? ???? ???? ??? ??? ?????, ?? ?????? ????? ????? ?? ???????",
  "queryConvert.about3": "3. HSV ??????????? ??? HSV ??? 0 ?? 1 ?? ???? ??? ????? ???, ?? ?????????? ?????????? ?? ???? ??????? ?? ??? ?????? ???",
  "queryConvert.about4": "4. RGB/HEX ???????? R, G ?? B ????? (0-255) ?? ??? ??? ?? ???? ?? ?? HEX ?? ??? ???? ????-???????? ???????? ???? ???",
  "queryConvert.about5": "5. RGB/CMYK ???????? RGB ?? ?????? ??? ??????? CMYK ???? ?? ??? ????-???????? ???????? ?? ?????? ???? ???",
  "queryConvert.about6": "6. HSV/CMYK ???????? ??????????? HSV ?? CMYK ?? ??? ???? ???????? ?? ?????? ???? ??, ?? ????? ??????? ????????? ??? ?????? ???",
  "queryConvert.about7": "7. RGB/HSV ???????? ???? RGB ????? ?? ??????????? HSV ?? ??? ?? ??? ???????? ???? ???",
  "queryConvert.about8": "8. CMYK/HEX ???????? ??????-?????? CMYK ????? ?? ???-?????? HEX ????? ?? ????? ?????? ??? ??? ???? ???",
  "queryConvert.about9": "9. ?????? ???? ?? ??? ??? ????? ??????? ??, ?? ?? ?????? ?? ?? ????? ??? ???? ???? ?? ???? ???",
  "queryConvert.tabs.common": "??????? ???????",
  "queryConvert.tabs.hsvNorm": "??????????? HSV",
  "queryConvert.tabs.rgbHex": "RGB/HEX",
  "queryConvert.tabs.rgbCmyk": "RGB/CMYK",
  "queryConvert.tabs.hsvCmyk": "HSV/CMYK",
  "queryConvert.tabs.rgbHsv": "RGB/HSV",
  "queryConvert.tabs.cmykHex": "CMYK/HEX",
  "queryConvert.labels.red": "??? (R:0-255)",
  "queryConvert.labels.green": "??? (G:0-255)",
  "queryConvert.labels.blue": "???? (B:0-255)",
  "queryConvert.labels.hexValue": "HEX ???",
  "queryPicker.aboutTitle": "??? ???? ?? ???? ???:",
  "queryPicker.about1": "1. ?????????? ??? ???? ?? ??? ?? ??? ??????",
  "queryPicker.about2": "2. ??? ????? ?? ???, ?? ???? ??????? ??? ??? ????? ??? ???? ????",
  "queryPicker.about3": "3. ?? ??? ??????/?????????? ?? ?? ?????? ???? ???",
  "queryPicker.about4": "4. ????? ???: ???-??? ?????? ?????? ?? ???? ??? ????? ??? ??? ???? ????",
  "queryPicker.luminance": "?????????",
  "queryPicker.brightness": "???",
  "queryGradients.categoryCss": "CSS ?????????",
  "queryGradients.categoryFresh": "?????",
  "queryGradients.categoryElegant": "?????",
  "queryGradients.countHint": "??? {{total}} ???????, ??????? ?????? {{current}}",
  "queryGradients.copyColorTitle": "??? ???? ????: {{value}}",
  "queryGradients.aboutTitle": "????????? ?? ???? ???:",
  "queryGradients.about1": "1. ?? ??? ??? ????????? CSS, ????? ?? ????? ??? ???? ??? ????? ????????? ????? ???? ???",
  "queryGradients.about2": "2. ?? ????? ???? ??? ??? ?? ????? ?????? ?????? ??? ???? ???? ????? ????? ?? ??? ?????? ?? ?????? ??????? ?????",
  "queryGradients.about3": "3. ????? ?? ????? ????????? ??? ???? ????? ?? ????? ???? HEX ???? ????, ?? ???????? ?? ????? ???? CSS ???? ?????",
  "queryGradients.about4": "4. CSS ?????? ??? ???? CSS ??? ???? ?? ??? CSS ???? ???? ?? ????? ????, ???? ?? ??? ??????? ?? ??? ????? ??? ????? ?? ?????",
  "queryWebsafe.clickCopyHex": "HEX ???? ???? ?? ??? ????? ????: {{value}}",
  "queryWebsafe.clickCopyRgb": "RGB ???? ???? ?? ??? ????? ????: {{value}}",
  "queryWebsafe.aboutTitle": "??? ??? ????? ?? ???? ???",
  "queryWebsafe.aboutDesc": "??? ??? ??? 216 ????? ?? ?? ???? ??, ?? 256-??? ??? ??? ??????? ???????? ?? ????? ????? ???? ??? ?????? ???????? ????? ????? ?? ?????? ???? ???, ??? ?? ??? ??? ??? ???? ???? ???????? ???? ?????????? ??? ?? ???? ????? ?????? ?? ??? ??? ?????? ???? HEX ?? RGB ???? ???? ?? ??? ??? ????? ?? ????? ?????",
  "queryRgb.searchPlaceholder": "HEX ?? RGB ???? ????",
  "queryRgb.search": "?????",
  "queryRgb.clearSearch": "??? ?????? ??? ???? ?? ?????? ?? ?????",
  "queryRgb.aboutTitle": "RGB ?? HEX ????? ?? ???? ???:",
  "queryRgb.about1": "1. RGB ?? ??? ???? ??, ?? ???????? ????? ??? ?????? ??? ?? ????? ???? ??; ?? ???, ??? ?? ???? ?? ?????? ??? ??????? ???",
  "queryRgb.about2": "2. HEX, RGB ?? ?????? ??; ?? ???????? ???? ?? ??????? ?????? ?? ??? ???????????? ???????? ?? ????? ???? ???",
  "queryRgb.about3": "3. ????? ??? 0 ?? F ?? ???? ???, ???? A?F ????? 10?15 ?? ???????????? ???? ????",
  "queryRgb.about4": "4. RGB ?? HEX ??-????? ??? ???? ?? ???? ???; ???? ?? ?? ?????? ??????",
  "queryRgb.notFound": "??? ??? ???? ??? ???? ????...",
  "queryCmyk.aboutTitle": "CMYK/RGB ?? ???? ???:",
  "queryCmyk.about1": "1. CMYK (Cyan, Magenta, Yellow, Black) ????????? ??? ????? ???? ???? ???-??? ???? ???",
  "queryCmyk.about2": "2. RGB (Red, Green, Blue) ?? ?????? ??? ???? ??, ?? ?????? ?? ?????? ??? ????? ???",
  "queryCmyk.about3": "3. ?? ??? ???? ????? ?? ??? ??????? CMYK ?? RGB ??? ????? ????? ??? ??? ???? ???",
  "queryPalette.newPaletteName": "????? {{count}}",
  "queryPalette.create": "?? ?????",
  "queryPalette.import": "???????",
  "queryPalette.exportAll": "??? ????????? ????",
  "queryPalette.created": "????? ???? ??",
  "queryPalette.updatedName": "????? ?? ??? ????? ???",
  "queryPalette.enterOrPickColor": "????? ??? ???? ???? ?? ?????",
  "queryPalette.invalidColor": "?????? ??? ???? HEX / RGB ??? ???? ?????",
  "queryPalette.added": "????? ??? ????? ???",
  "queryPalette.removed": "????? ?? ????? ???",
  "queryPalette.pickToAdd": "????? ?? ??????",
  "queryPalette.add": "??????",
  "queryPalette.addCurrentPicked": "??????? ???? ??? ??????",
  "queryPalette.inputPlaceholder": "#000000 ?? RGB",
  "queryPalette.exportedOne": "????? ????????? ?? ??",
  "queryPalette.exportedAll": "??? ????? ????????? ?? ???",
  "queryPalette.importedPaletteName": "??????? ?? ?? ?????",
  "queryPalette.noValidImport": "??? ??? ????? ???? ???? ????",
  "queryPalette.importedCount": "{{count}} ????? ??????? ?? ???",
  "queryPalette.importFailed": "??????? ????? ????? JSON ???????? ??????",
  "queryPalette.confirmDelete": "????? \"{{name}}\" ??????",
  "queryPalette.deleted": "????? ??? ?? ??",
  "queryPalette.clear": "??? ????",
  "queryReference.title": "??? ?????? ??????",
  "queryReference.preview": "????????",
  "queryReference.name": "???",
  "queryReference.cmykApprox": "CMYK (????????)",
  "queryReference.aboutTitle": "??? ?????? ?????? ?? ???? ???:",
  "queryReference.about1": "1. ?? ??? ??????? ???? ????? ?? ?????? ?????? ???? ??, ?????? ????????, ???, HEX, RGB ?? ???????? CMYK ??? ????? ????",
  "queryReference.about2": "2. ?? ??? ??????? ?? ??? ????? ?? ????? ????? ?? ???? ??? ?? ?????? ??????? ??? ??? ????? ?????? ?? ??? ?????? ?? ??? ??? ????? ?? ???? ????",
  "queryReference.about3": "3. ????? ???: ?????? ?? CMYK ??? ?????? ?????? ??? ?? ???? ?????? ?????? ?? ??? ???? ?????? ????????? ?? ??? ???????? ?????? ?????? ?? ????? ?????"
}
